graia/saya/__init__.py
graia/saya/behaviour/__init__.py
graia/saya/behaviour/context.py
graia/saya/behaviour/entity.py
graia/saya/behaviour/interface.py
graia/saya/builtins/__init__.py
graia/saya/builtins/broadcast/__init__.py
graia/saya/builtins/broadcast/behaviour.py
graia/saya/builtins/broadcast/schema.py
graia/saya/builtins/broadcast/shortcut.py
graia/saya/channel.py
graia/saya/context.py
graia/saya/creator.py
graia/saya/cube.py
graia/saya/event.py
graia/saya/factory.py
graia/saya/schema.py
graia_saya-0.0.20.dist-info/METADATA
graia_saya-0.0.20.dist-info/WHEEL
graia_saya-0.0.20.dist-info/entry_points.txt
graia_saya-0.0.20.dist-info/RECORD
