Metadata-Version: 2.1
Name: graia-saya
Version: 0.0.20
Summary: a modular implementation with modern design and injection
Author-Email: GreyElaina <31543961+GreyElaina@users.noreply.github.com>
License: MIT
Requires-Python: <4.0,>=3.8
Requires-Dist: importlib-metadata>=3.6.0
Requires-Dist: loguru<1.0,>=0.6.0
Requires-Dist: typing-extensions>=4.5.0
Provides-Extra: broadcast
Requires-Dist: graia-broadcast>=0.23.0; extra == "broadcast"
Provides-Extra: scheduler
Requires-Dist: graia-scheduler<1.0.0,>=0.2.0; extra == "scheduler"
